{
  "name" : "Patient Registration",
  "uuid" : "af29950e-93c6-4ffc-88c4-46d08dc0498f",
  "formType" : "IndividualProfile",
  "formElementGroups" : [ {
    "uuid" : "e5c736fb-2163-4a47-9985-f1a81521e476",
    "name" : "Additional Details",
    "displayOrder" : 1.0,
    "display" : "Additional Details",
    "formElements" : [ {
      "name" : "Patient Identifier",
      "uuid" : "7930e18d-d3e7-4713-878f-5089fb706027",
      "keyValues" : [ {
        "key" : "IdSourceUUID",
        "value" : "0e58ba25-b097-461f-bba5-68c809908876"
      } ],
      "concept" : {
        "name" : "Patient Identifier",
        "uuid" : "ffd35c7d-7414-4f0f-8fdd-7de5e48770da",
        "dataType" : "Id",
        "answers" : [ ],
        "active" : true,
        "keyValues" : [ ]
      },
      "displayOrder" : 1.0,
      "type" : "SingleSelect",
      "mandatory" : true
    }, {
      "name" : "ABHA Address",
      "uuid" : "e492ca11-c812-4a62-bce8-544b3943921e",
      "keyValues" : [ {
        "key" : "editable",
        "value" : false
      } ],
      "concept" : {
        "name" : "ABHA Address",
        "uuid" : "0703cc26-f951-4fad-a575-04da252ef68b",
        "dataType" : "Text",
        "answers" : [ ],
        "active" : true,
        "keyValues" : [ ]
      },
      "displayOrder" : 2.0,
      "type" : "SingleSelect",
      "mandatory" : false
    }, {
      "name" : "ABHA Number",
      "uuid" : "a0dba349-6d09-46fb-8a30-3a60b1ddb908",
      "keyValues" : [ {
        "key" : "editable",
        "value" : false
      } ],
      "concept" : {
        "name" : "ABHA Number",
        "uuid" : "e47be326-fad5-46ff-a0b8-e76c393b146f",
        "dataType" : "Text",
        "answers" : [ ],
        "active" : true,
        "keyValues" : [ ]
      },
      "displayOrder" : 3.0,
      "type" : "SingleSelect",
      "mandatory" : false
    }, {
      "name" : "RCH ID",
      "uuid" : "edde014f-568d-4971-b886-d07fef028a17",
      "keyValues" : [ ],
      "concept" : {
        "name" : "RCH ID",
        "uuid" : "18298f4d-79ec-44b0-8f8b-1f1c5505effc",
        "dataType" : "Numeric",
        "answers" : [ ],
        "active" : true,
        "keyValues" : [ ]
      },
      "displayOrder" : 4.0,
      "type" : "SingleSelect",
      "mandatory" : false
    }, {
      "name" : "Nikshay ID",
      "uuid" : "6c76db30-a580-4f41-a1f8-80c0d25ded4e",
      "keyValues" : [ ],
      "concept" : {
        "name" : "Nikshay ID",
        "uuid" : "50ee923b-d2d5-42ec-874d-e3ccd9dd4895",
        "dataType" : "Numeric",
        "answers" : [ ],
        "active" : true,
        "keyValues" : [ ]
      },
      "displayOrder" : 5.0,
      "type" : "SingleSelect",
      "mandatory" : false
    }, {
      "name" : "Father/Mother's Name",
      "uuid" : "42ce9bbc-4243-47d9-8a70-8aa104ea1203",
      "keyValues" : [ ],
      "concept" : {
        "name" : "Father/Mother's Name",
        "uuid" : "9092d96c-ed9e-416b-9a50-606f003a6b38",
        "dataType" : "Text",
        "answers" : [ ],
        "active" : true,
        "keyValues" : [ ]
      },
      "displayOrder" : 6.0,
      "type" : "SingleSelect",
      "mandatory" : false
    }, {
      "name" : "Phone Number",
      "uuid" : "fd2f03b9-2e46-4a8e-b9a9-68fbbcc9b9a2",
      "keyValues" : [ ],
      "concept" : {
        "name" : "Phone Number",
        "uuid" : "799681f1-9733-4d6d-8c3b-072afa186572",
        "dataType" : "Text",
        "answers" : [ ],
        "active" : true,
        "keyValues" : [ ]
      },
      "displayOrder" : 7.0,
      "type" : "SingleSelect",
      "validFormat" : {
        "regex" : "^([1-9]{1}[0-9]{9})$",
        "descriptionKey" : "Phone Number should be 10 digits"
      },
      "mandatory" : true
    } ],
    "timed" : false
  } ],
  "decisionRule" : "",
  "visitScheduleRule" : "",
  "validationRule" : "",
  "checklistsRule" : "",
  "decisionConcepts" : [ ]
}